scisuitplot/__init__.py
scisuitplot/_ctypeslib.py
scisuitplot/app.py
scisuitplot/boost_math_tr1-vc143-mt-x64-1_81.dll
scisuitplot/gdi.py
scisuitplot/jpeg62.dll
scisuitplot/liblzma.dll
scisuitplot/libpng16.dll
scisuitplot/pcre2-16.dll
scisuitplot/pybind311.dll
scisuitplot/scisuit_core.dll
scisuitplot/scisuit_plotter.dll
scisuitplot/settings.py
scisuitplot/tiff.dll
scisuitplot/util.py
scisuitplot/wxbase32u_vc_custom.dll
scisuitplot/wxmsw32u_core_vc_custom.dll
scisuitplot/wxmsw32u_html_vc_custom.dll
scisuitplot/zlib1.dll
scisuitplot/multivariate/__init__.py
scisuitplot/multivariate/_biplot.py
scisuitplot/multivariate/_loading.py
scisuitplot/multivariate/_outlier.py
scisuitplot/multivariate/_score.py
scisuitplot/multivariate/_scree.py
scisuitplot-2.0.0.dist-info/licenses/LICENSE
scisuitplot-2.0.0.dist-info/METADATA
scisuitplot-2.0.0.dist-info/WHEEL
scisuitplot-2.0.0.dist-info/top_level.txt
scisuitplot-2.0.0.dist-info/RECORD
